[
  {
    "id": "mon_bloodsucker",
    "type": "MONSTER",
    "name": { "str": "bloodsucker" },
    "description": "Bloodsuckers are almost legendary creatures.  They are fast, resilient and can turn invisible.  Not many people have left alive to tell the story after encountering these abominations.",
    "default_faction": "zombie",
    "bodytype": "human",
    "species": [ "ZOMBIE", "HUMAN" ],
    "volume": "62500 ml",
    "weight": "81500 g",
    "hp": 180,
    "speed": 130,
    "material": [ "flesh" ],
    "symbol": "@",
    "color": "light_red",
    "aggression": 100,
    "morale": 100,
    "melee_skill": 6,
    "melee_dice": 2,
    "melee_dice_sides": 4,
    "melee_cut": 4,
    "dodge": 4,
    "armor_bash": 6,
    "armor_cut": 4,
    "armor_bullet": 5,
    "vision_day": 35,
    "vision_night": 45,
    "harvest": "zombie",
    "special_attacks": [
      { "id": "scratch", "damage_max_instance": [ { "damage_type": "cut", "amount": 12 } ] },
      {
        "type": "bite",
        "cooldown": 10,
        "damage_max_instance": [ { "damage_type": "stab", "amount": 12, "armor_multiplier": 0.6 } ]
      }
    ],
    "death_function": [ "NORMAL" ],
    "flags": [ "SEES", "HEARS", "SMELLS", "WARM","GOODHEARING", "NIGHT_INVISIBILITY", "HIT_AND_RUN", "PATH_AVOID_DANGER_1", "HARDTOSHOOT", "POISON" ]
  },
  {
    "id": "mon_bloodsucker_alpha",
    "type": "MONSTER",
    "copy-from": "mon_bloodsucker",
    "name": { "str": "alpha bloodsucker" },
    "description": "This mostrosity is a head taller than it's friends.  Superhumanly strong, fast and agile.",
    "volume": "100000 ml",
    "weight": "120 kg",
    "hp": 340,
    "speed": 150,
    "color": "red",
    "melee_skill": 8,
    "melee_dice": 3,
    "melee_dice_sides": 6,
    "melee_cut": 8,
    "dodge": 6,
    "armor_bash": 9,
    "armor_cut": 6,
    "armor_bullet": 10,
    "special_attacks": [
      { "id": "scratch", "damage_max_instance": [ { "damage_type": "cut", "amount": 22 } ] },
      {
        "type": "bite",
        "cooldown": 8,
        "damage_max_instance": [ { "damage_type": "stab", "amount": 20, "armor_multiplier": 0.4 } ]
      }
    ]
},
{
    "id": "mon_snork",
    "type": "MONSTER",
    "name": { "str": "snork" },
    "description": "The Snork is a horrifically mutated human soldier or Stalker, still wearing tattered remains of his uniform, boots and a gas mask with cracked eyepieces, and a flailing hose.  Exposure to radiation and anomalies in the wake of the second Chernobyl disaster has destroyed the human mind, leaving a feral, vicious beast psyche and a twisted body in its place, creating a dangerous predator.",
    "default_faction": "zombie",
    "bodytype": "human",
    "species": [ "ZOMBIE", "HUMAN" ],
    "volume": "62500 ml",
    "weight": "81500 g",
    "hp": 100,
    "speed": 115,
    "material": [ "flesh" ],
    "symbol": "Z",
    "color": "brown",
    "looks_like": "mon_zombie_predator",
    "aggression": 100,
    "morale": 100,
    "melee_skill": 5,
    "melee_dice": 2,
    "melee_dice_sides": 4,
    "melee_cut": 4,
    "dodge": 4,
    "armor_bash": 4,
    "armor_cut": 6,
    "armor_bullet": 6,
    "vision_day": 45,
    "vision_night": 25,
    "harvest": "zombie",
    "path_settings": { "max_dist": 5 },
    "special_attacks": [
      { "type": "leap", "cooldown": 10, "max_range": 4 },
      {
        "type": "bite",
        "cooldown": 10,
        "damage_max_instance": [ { "damage_type": "stab", "amount": 8, "armor_multiplier": 0.8 } ]
      }
    ],
    "death_drops": "mon_snork_death_drops",
    "death_function": [ "NORMAL" ],
    "flags": [ "SEES", "HEARS", "SMELLS", "WARM", "PATH_AVOID_DANGER_1", "BASHES", "POISON", "FILTHY", "KEENNOSE"]
},
  {
    "id": "mon_controller",
    "type": "MONSTER",
    "name": { "str": "controller" },
    "description": "A rare mutant seen near to the center of the Zone, it bears a superficial resemblance to a humanoid with a disproportionately large head.  Despite their appearance, they are highly intelligent, possess good perception and the ability to control the behavior of less developed creatures.  Mature specimens are capable of taking control of a human's mind.",
    "default_faction": "zombie",
    "bodytype": "human",
    "species": [ "ZOMBIE", "HUMAN" ],
    "diff": 20,
    "volume": "62500 ml",
    "weight": "81500 g",
    "hp": 180,
    "speed": 90,
    "material": [ "flesh" ],
    "symbol": "@",
    "color": "pink_red",
    "looks_like": "mon_zombie_master",
    "aggression": 5,
    "morale": 100,
    "melee_skill": 5,
    "melee_dice": 2,
    "melee_dice_sides": 6,
    "melee_cut": 0,
    "dodge": 4,
    "armor_bash": 2,
    "armor_cut": 2,
    "armor_bullet": 2,
    "vision_day": 55,
    "vision_night": 20,
    "harvest": "zombie",
    "path_settings": { "max_dist": 10 },
    "anger_triggers": [ "HURT", "PLAYER_CLOSE", "PLAYER_WEAK" ],
    "death_drops": "default_zombie_death_drops",
    "death_function": [ "NORMAL" ],
        "special_attacks": [
      { "type": "spell", "spell_data": { "id": "mi-go_slaver_beam", "min_level": 3 }, "cooldown": 100 }, [ "FEAR_PARALYZE", 9 ]
    ],
    "flags": [
      "SEES",
      "HEARS",
      "SMELLS",
      "WARM",
      "POISON",
      "PATH_AVOID_DANGER_2",
      "CAN_OPEN_DOORS",
      "PRIORITIZE_TARGETS",
      "FILTHY",
      "HARDTOSHOOT"
    ]
  }
]